ISeqDb/ISeqDb.py
ISeqDb/__init__.py
ISeqDb/create_db.py
ISeqDb/find_seqs.py
ISeqDb/inspect_db.py
iseqdb-0.0.6.dist-info/licenses/LICENSE
iseqdb-0.0.6.dist-info/METADATA
iseqdb-0.0.6.dist-info/WHEEL
iseqdb-0.0.6.dist-info/entry_points.txt
iseqdb-0.0.6.dist-info/top_level.txt
iseqdb-0.0.6.dist-info/RECORD
