Metadata-Version: 2.4
Name: ISeqDb
Version: 0.0.6
Summary: ISeqDb - Identify Sequences in Databases
Home-page: https://github.com/hts-tools/iseqdb
Author: Nico Salmaso
Author-email: nico.salmaso@fmach.it
Classifier: Programming Language :: Python :: 3
Classifier: License :: OSI Approved :: GNU General Public License v3 (GPLv3)
Requires-Python: >=3.10
License-File: LICENSE
Requires-Dist: pandas
Dynamic: license-file
